{
  "id": "importance_sampling",
  "category": "probability",
  "difficulty": 2,
  "summary": "TWO_COLUMN importance sampling. LEFT axes with BLUE p=N(0, 1) and ORANGE q=N(1.5, 1) densities + 400 pre-drawn samples from q colored RED (low weight) → YELLOW (high weight) revealed via ValueTracker n_tr. always_redraw dot cloud + live running estimator of E_p[X²]=1. RIGHT has N, estimator, error.",
  "tags": ["importance_sampling", "weighted_samples", "proposal_density", "monte_carlo", "value_tracker", "always_redraw"],
  "apis": ["Axes", "Dot", "DecimalNumber", "ValueTracker", "always_redraw", "Tex"]
}
